definable/__init__.py
definable/base/__init__.py
definable/base/agent.py
definable/base/models.py
definable/cli/__init__.py
definable/cli/build.py
definable/cli/config.py
definable/cli/init.py
definable/cli/main.py
definable/cli/push.py
definable/cli/serve.py
definable/server/__init__.py
definable/server/app.py
definable/server/main.py
definable/templates/Dockerfile.jinja2
definable/templates/docker-compose.yml.jinja2
definable/templates/requirements.txt.jinja2
definable/utils/__init__.py
definable/utils/code_packager.py
definable/utils/config_manager.py
definable/utils/docker_builder.py
definable/utils/yaml_parser.py
definable-0.2.5.dist-info/METADATA
definable-0.2.5.dist-info/WHEEL
definable-0.2.5.dist-info/entry_points.txt
definable-0.2.5.dist-info/top_level.txt
definable-0.2.5.dist-info/RECORD
