Metadata-Version: 2.4
Name: definable
Version: 0.2.5
Summary: Infrastructure for building and deploying AI agents
Home-page: https://github.com/definable/definable
Author: Definable Team
Author-email: team@definable.ai
Classifier: Development Status :: 3 - Alpha
Classifier: Intended Audience :: Developers
Classifier: License :: OSI Approved :: MIT License
Classifier: Programming Language :: Python :: 3
Classifier: Programming Language :: Python :: 3.9
Classifier: Programming Language :: Python :: 3.10
Classifier: Programming Language :: Python :: 3.11
Classifier: Programming Language :: Python :: 3.12
Requires-Python: >=3.9
Requires-Dist: fastapi>=0.100.0
Requires-Dist: uvicorn[standard]>=0.20.0
Requires-Dist: pydantic>=2.0.0
Requires-Dist: click>=8.0.0
Requires-Dist: docker>=6.0.0
Requires-Dist: PyYAML>=6.0.0
Requires-Dist: Jinja2>=3.0.0
Requires-Dist: urllib3<2.0.0,>=1.26.0
Dynamic: author
Dynamic: author-email
Dynamic: classifier
Dynamic: description
Dynamic: description-content-type
Dynamic: home-page
Dynamic: requires-dist
Dynamic: requires-python
Dynamic: summary
